{
  "indicator": "FRPMSchoolYear",
  "keywords": [
    "eligible",
    "students",
    "meals",
    "food",
    "hunger",
    "reduced",
    "free",
    "price",
    "cost",
    "lunches",
    "school",
    "year"
  ],
  "years": ["2016"],
  "categories": ["health", "education"],
  "counties": {
    "california": { "ranks": [""], "totals": [54] },
    "alameda": { "ranks": [54], "totals": [41] },
    "alpine": { "ranks": [1], "totals": [96] },
    "amador": { "ranks": [45], "totals": [48] },
    "butte": { "ranks": [24], "totals": [55] },
    "calaveras": { "ranks": [47], "totals": [46] },
    "colusa": { "ranks": [2], "totals": [69] },
    "contraCosta": { "ranks": [30], "totals": [53] },
    "delNorte": { "ranks": [43], "totals": [48] },
    "elDorado": { "ranks": [32], "totals": [53] },
    "fresno": { "ranks": [4], "totals": [65] },
    "glenn": { "ranks": [16], "totals": [58] },
    "humboldt": { "ranks": [48], "totals": [46] },
    "imperial": { "ranks": [14], "totals": [58] },
    "inyo": { "ranks": [58], "totals": [22] },
    "kern": { "ranks": [7], "totals": [63] },
    "kings": { "ranks": [21], "totals": [57] },
    "lake": { "ranks": [31], "totals": [53] },
    "lassen": { "ranks": [55], "totals": [39] },
    "losAngeles": { "ranks": [38], "totals": [49] },
    "madera": { "ranks": [11], "totals": [61] },
    "marin": { "ranks": [34], "totals": [52] },
    "mariposa": { "ranks": [46], "totals": [46] },
    "mendocino": { "ranks": [40], "totals": [49] },
    "merced": { "ranks": [9], "totals": [62] },
    "modoc": { "ranks": [6], "totals": [63] },
    "mono": { "ranks": [56], "totals": [33] },
    "monterey": { "ranks": [19], "totals": [57] },
    "napa": { "ranks": [50], "totals": [45] },
    "nevada": { "ranks": [57], "totals": [26] },
    "orange": { "ranks": [13], "totals": [60] },
    "placer": { "ranks": [35], "totals": [52] },
    "plumas": { "ranks": [53], "totals": [42] },
    "riverside": { "ranks": [10], "totals": [61] },
    "sacramento": { "ranks": [28], "totals": [55] },
    "sanBenito": { "ranks": [15], "totals": [58] },
    "sanBernardino": { "ranks": [17], "totals": [58] },
    "sanDiego": { "ranks": [42], "totals": [49] },
    "sanFrancisco": { "ranks": [51], "totals": [44] },
    "sanJoaquin": { "ranks": [25], "totals": [55] },
    "sanLuisObispo": { "ranks": [49], "totals": [45] },
    "sanMateo": { "ranks": [36], "totals": [52] },
    "santaBarbara": { "ranks": [12], "totals": [60] },
    "santaClara": { "ranks": [41], "totals": [49] },
    "santaCruz": { "ranks": [44], "totals": [48] },
    "shasta": { "ranks": [26], "totals": [55] },
    "sierra": { "ranks": [23], "totals": [55] },
    "siskiyou": { "ranks": [33], "totals": [52] },
    "solano": { "ranks": [37], "totals": [50] },
    "sonoma": { "ranks": [52], "totals": [44] },
    "stanislaus": { "ranks": [18], "totals": [58] },
    "sutter": { "ranks": [39], "totals": [49] },
    "tehama": { "ranks": [3], "totals": [66] },
    "trinity": { "ranks": [22], "totals": [55] },
    "tulare": { "ranks": [8], "totals": [62] },
    "tuolumne": { "ranks": [29], "totals": [54] },
    "ventura": { "ranks": [27], "totals": [55] },
    "yolo": { "ranks": [20], "totals": [57] },
    "yuba": { "ranks": [5], "totals": [64] }
  },
  "semantics": {
    "descriptor": "eligible",
    "who": "students",
    "what": "received free or reduced-price meals during the school year",
    "label": "Eligible students who received free or reduced-price meals during the school year",
    "shorthand": "Free/reduced $ meals, school year"
  }
}
